MANIFEST.in
README.md
req.py
requirements.txt
setup.py
algoneer_datasets/__init__.py
algoneer_datasets/py.typed
algoneer_datasets.egg-info/PKG-INFO
algoneer_datasets.egg-info/SOURCES.txt
algoneer_datasets.egg-info/dependency_links.txt
algoneer_datasets.egg-info/not-zip-safe
algoneer_datasets.egg-info/requires.txt
algoneer_datasets.egg-info/top_level.txt
algoneer_datasets/adult/__init__.py
algoneer_datasets/adult/data.csv.gz
algoneer_datasets/adult/dataset.yml
algoneer_datasets/adult/test_loading.py
algoneer_datasets/bike_sharing/__init__.py
algoneer_datasets/bike_sharing/algorithms.py
algoneer_datasets/bike_sharing/data.csv.gz
algoneer_datasets/bike_sharing/dataset.yml
algoneer_datasets/bike_sharing/test_loading.py